zllm_lib/__init__.py
zllm_lib/py.typed
zllm_lib-0.1.0.dist-info/METADATA
zllm_lib-0.1.0.dist-info/WHEEL
zllm_lib-0.1.0.dist-info/licenses/LICENSE
zllm_lib-0.1.0.dist-info/RECORD
